dmhouse/LICENSE
dmhouse/__init__.py
dmhouse/_dmhouse.py
dmhouse/_version.py
dmhouse/bspc
dmhouse/deepmind_lab.so
dmhouse/libdmlab_headless_hw.so
dmhouse/libdmlab_headless_sw.so
dmhouse/baselab/assets.pk3
dmhouse/baselab/assets_bots.pk3
dmhouse/baselab/assets_oa.pk3
dmhouse/baselab/default.cfg
dmhouse/baselab/q3config.cfg
dmhouse/baselab/vm.pk3
dmhouse/baselab/game_scripts/common/bots.lua
dmhouse/baselab/game_scripts/common/color_bots.lua
dmhouse/baselab/game_scripts/common/colors.lua
dmhouse/baselab/game_scripts/common/combinatorics.lua
dmhouse/baselab/game_scripts/common/custom_entities.lua
dmhouse/baselab/game_scripts/common/game_rewards.lua
dmhouse/baselab/game_scripts/common/game_types.lua
dmhouse/baselab/game_scripts/common/geometric_pickups.lua
dmhouse/baselab/game_scripts/common/helpers.lua
dmhouse/baselab/game_scripts/common/human_recognisable_pickups.lua
dmhouse/baselab/game_scripts/common/inventory.lua
dmhouse/baselab/game_scripts/common/log.lua
dmhouse/baselab/game_scripts/common/make_map.lua
dmhouse/baselab/game_scripts/common/pickups.lua
dmhouse/baselab/game_scripts/common/position_trigger.lua
dmhouse/baselab/game_scripts/common/random.lua
dmhouse/baselab/game_scripts/common/screen_message.lua
dmhouse/baselab/game_scripts/common/set.lua
dmhouse/baselab/game_scripts/common/team_colors.lua
dmhouse/baselab/game_scripts/common/timer.lua
dmhouse/baselab/game_scripts/common/transform.lua
dmhouse/baselab/game_scripts/common/tuple.lua
dmhouse/baselab/game_scripts/custom/common.lua
dmhouse/baselab/game_scripts/custom/goal_distance_decorator.lua
dmhouse/baselab/game_scripts/custom/hit_goal_decorator.lua
dmhouse/baselab/game_scripts/custom/house_factory.lua
dmhouse/baselab/game_scripts/custom/house_layout.lua
dmhouse/baselab/game_scripts/custom/house_theme.lua
dmhouse/baselab/game_scripts/custom/objects.lua
dmhouse/baselab/game_scripts/custom/observe_goal_decorator.lua
dmhouse/baselab/game_scripts/custom/procedural.lua
dmhouse-1.0.10.dist-info/LICENSE
dmhouse-1.0.10.dist-info/METADATA
dmhouse-1.0.10.dist-info/WHEEL
dmhouse-1.0.10.dist-info/top_level.txt
dmhouse-1.0.10.dist-info/RECORD
