Metadata-Version: 2.1
Name: dmhouse
Version: 1.0.10
Summary: DMHouse 3D environment simulator
Home-page: https://github.com/jkulhanek/dmlab-vn
Author: Jonas Kulhanek
Author-email: jonas.kulhanek@live.com
License: MIT
Platform: UNKNOWN
Classifier: License :: OSI Approved :: MIT License
Classifier: Programming Language :: Python :: 3
License-File: LICENSE
Requires-Dist: numpy (==1.19.5)
Requires-Dist: six (>=1.10.0)
Requires-Dist: gym
